{
 "actions": [],
 "autoname": "autoincrement",
 "creation": "2023-04-23 12:35:58.475233",
 "doctype": "DocType",
 "editable_grid": 1,
 "engine": "InnoDB",
 "field_order": [
  "min_pax",
  "max_pax",
  "transportation_type",
  "daily_rate",
  "days",
  "extra_charge",
  "rate"
 ],
 "fields": [
  {
   "fieldname": "min_pax",
   "fieldtype": "Int",
   "in_list_view": 1,
   "label": "Min Pax"
  },
  {
   "fieldname": "max_pax",
   "fieldtype": "Int",
   "in_list_view": 1,
   "label": "Max Pax"
  },
  {
   "fieldname": "transportation_type",
   "fieldtype": "Link",
   "in_list_view": 1,
   "label": "Transportation Type",
   "options": "Vehicle Types"
  },
  {
   "fieldname": "rate",
   "fieldtype": "Currency",
   "in_list_view": 1,
   "label": "Total Rate",
   "read_only": 1
  },
  {
   "fieldname": "daily_rate",
   "fieldtype": "Currency",
   "in_list_view": 1,
   "label": "Daily Rate"
  },
  {
   "fieldname": "days",
   "fieldtype": "Float",
   "in_list_view": 1,
   "label": "Days"
  },
  {
   "fieldname": "extra_charge",
   "fieldtype": "Currency",
   "in_list_view": 1,
   "label": "Extra Charge"
  }
 ],
 "index_web_pages_for_search": 1,
 "istable": 1,
 "links": [],
 "modified": "2023-04-23 15:30:53.026240",
 "modified_by": "Administrator",
 "module": "Tour Managements",
 "name": "Tour Package Transportation Rate",
 "naming_rule": "Random",
 "owner": "Administrator",
 "permissions": [],
 "sort_field": "modified",
 "sort_order": "DESC",
 "states": []
}